README.md
setup.cfg
setup.py
steppy/__init__.py
steppy/adapter.py
steppy/base.py
steppy/utils.py
steppy.egg-info/PKG-INFO
steppy.egg-info/SOURCES.txt
steppy.egg-info/dependency_links.txt
steppy.egg-info/not-zip-safe
steppy.egg-info/requires.txt
steppy.egg-info/top_level.txt