Metadata-Version: 1.1
Name: steppy
Version: 0.1.14
Summary: A lightweight, open-source, Python library for fast and reproducible experimentation
Home-page: https://github.com/minerva-ml/steppy
Author: Kamil A. Kaczmarek, Jakub Czakon
Author-email: kamil.kaczmarek@neptune.ml, jakub.czakon@neptune.ml
License: MIT
Download-URL: https://github.com/minerva-ml/steppy/archive/0.1.14.tar.gz
Keywords: machine-learning,reproducibility,pipeline,data-science
Platform: UNKNOWN
